tasomasa_filler/__init__.py
tasomasa_filler/filler.py
test_pack/__init__.py
test_pack/hello_module.py
test_pack/main.py
test_pack_yasak/__init__.py
test_pack_yasak/hello_module.py
test_pack_yasak/main.py
test_pack_yasak2/__init__.py
test_pack_yasak2/hello_module.py
test_pack_yasak2/main.py
tasomasa_filter-0.1.2.dist-info/METADATA
tasomasa_filter-0.1.2.dist-info/WHEEL
tasomasa_filter-0.1.2.dist-info/top_level.txt
tasomasa_filter-0.1.2.dist-info/RECORD
