Metadata-Version: 2.1
Name: tasomasa-filter
Version: 0.1.2
Summary: my filler
Home-page: UNKNOWN
Author: yasak
Author-email: yamato02031996@gmail.com
License: 42Tokyo_piscine101
Platform: UNKNOWN
Requires-Python: >=3.7
